bytesviewapi/__init__.py
bytesviewapi/api_authentication.py
bytesviewapi/bytesviewapi_client.py
bytesviewapi/bytesviewapi_exception.py
bytesviewapi/constants.py
bytesviewapi/helpers.py
bytesviewapi/utils.py
bytesviewapi-0.1.6.dist-info/LICENSE
bytesviewapi-0.1.6.dist-info/METADATA
bytesviewapi-0.1.6.dist-info/WHEEL
bytesviewapi-0.1.6.dist-info/top_level.txt
bytesviewapi-0.1.6.dist-info/RECORD
