Metadata-Version: 2.1
Name: bytesviewapi
Version: 0.1.6
Summary: Python library for bytesview client-API Call
Home-page: https://github.com/algodommedia/bytesviewapi-python
Author: Bytesview
Author-email: contact@bytesview.com
License: MIT
Keywords: byteviewapi,senitment,emotion,keywords,semantic,name-entity,name-gender,intent,feature
Platform: UNKNOWN
Classifier: Development Status :: 2 - Pre-Alpha
Classifier: Intended Audience :: Developers
Classifier: Intended Audience :: Customer Service
Classifier: License :: OSI Approved :: MIT License
Classifier: Programming Language :: Python :: 3
Classifier: Programming Language :: Python :: 3.5
Classifier: Programming Language :: Python :: 3.6
Classifier: Programming Language :: Python :: 3.7
Classifier: Programming Language :: Python :: 3.8
Classifier: Programming Language :: Python :: 3.9
Requires-Python: >=3.5
Requires-Dist: requests (<3.0.0)
